pg_audit/__init__.py
pg_audit/cli.py
pg_audit/context.py
pg_audit/revert.py
pg_audit/schema.py
pg_audit/settings.py
pg_audit/triggers.py
pg_audit/utils.py
pg_audit/integrations/__init__.py
pg_audit/integrations/django/__init__.py
pg_audit/integrations/django/admin.py
pg_audit/integrations/django/apps.py
pg_audit/integrations/django/audit.py
pg_audit/integrations/django/hooks.py
pg_audit/integrations/django/middleware.py
pg_audit/integrations/django/mixins.py
pg_audit/integrations/django/models.py
pg_audit/integrations/django/settings.py
pg_audit/integrations/django/shell_context.py
pg_audit/integrations/django/utils.py
pg_audit/integrations/django/management/__init__.py
pg_audit/integrations/django/management/commands/__init__.py
pg_audit/integrations/django/management/commands/audit_add_partitions.py
pg_audit/integrations/django/migrations/0001_initial.py
pg_audit/integrations/django/migrations/__init__.py
pg_audit/integrations/django/templates/audit/object_history.html
pg_audit/integrations/django/templatetags/__init__.py
pg_audit/integrations/django/templatetags/audit_tags.py
pg_audit-0.1.20.dist-info/licenses/LICENSE
pg_audit-0.1.20.dist-info/METADATA
pg_audit-0.1.20.dist-info/WHEEL
pg_audit-0.1.20.dist-info/entry_points.txt
pg_audit-0.1.20.dist-info/top_level.txt
pg_audit-0.1.20.dist-info/RECORD
