Metadata-Version: 2.4
Name: pg_audit
Version: 0.1.20
Summary: PostgreSQL audit system for tracking database changes with rich contextual information
Author-email: Andrei Karbanovich <andrey.karbanovich@icloud.com>
License: MIT
Project-URL: Homepage, https://github.com/tauvin/pg_audit
Project-URL: BugTracker, https://github.com/tauvin/pg_audit/issues
Project-URL: Documentation, https://pg-audit.readthedocs.io/
Keywords: postgresql,audit,django,database,triggers
Classifier: Development Status :: 4 - Beta
Classifier: Intended Audience :: Developers
Classifier: License :: OSI Approved :: MIT License
Classifier: Programming Language :: Python :: 3
Classifier: Programming Language :: Python :: 3.8
Classifier: Programming Language :: Python :: 3.9
Classifier: Programming Language :: Python :: 3.10
Classifier: Programming Language :: Python :: 3.11
Classifier: Programming Language :: Python :: 3.12
Classifier: Programming Language :: Python :: 3.13
Classifier: Framework :: Django
Classifier: Topic :: Database
Classifier: Topic :: Software Development :: Libraries :: Python Modules
Requires-Python: >=3.8
License-File: LICENSE
Requires-Dist: typer>=0.9
Requires-Dist: psycopg[binary]>=3.1
Requires-Dist: pydantic>=2.5
Requires-Dist: structlog>=23.0
Requires-Dist: dateutils>=0.6.12
Provides-Extra: django
Requires-Dist: Django>=4.2; extra == "django"
Dynamic: license-file
